flaqes/__init__.py
flaqes/api.py
flaqes/cli.py
flaqes/py.typed
flaqes/analysis/__init__.py
flaqes/analysis/pattern_matcher.py
flaqes/analysis/role_detector.py
flaqes/analysis/tension_analyzer.py
flaqes/core/__init__.py
flaqes/core/intent.py
flaqes/core/schema_graph.py
flaqes/core/types.py
flaqes/introspection/__init__.py
flaqes/introspection/base.py
flaqes/introspection/ddl_parser.py
flaqes/introspection/postgresql.py
flaqes/introspection/registry.py
flaqes/patterns/__init__.py
flaqes/report/__init__.py
flaqes-0.2.0.dist-info/METADATA
flaqes-0.2.0.dist-info/WHEEL
flaqes-0.2.0.dist-info/entry_points.txt
flaqes-0.2.0.dist-info/licenses/LICENSE
flaqes-0.2.0.dist-info/RECORD
