Metadata-Version: 2.4
Name: flaqes
Version: 0.2.0
Summary: A schema critic for databases - analyze structure, surface trade-offs, propose alternatives
Author: Bruno Peixoto
License: MIT
License-File: LICENSE
Keywords: analysis,database,design,postgresql,schema
Classifier: Development Status :: 3 - Alpha
Classifier: Intended Audience :: Developers
Classifier: License :: OSI Approved :: MIT License
Classifier: Programming Language :: Python :: 3
Classifier: Programming Language :: Python :: 3.13
Classifier: Topic :: Database
Classifier: Typing :: Typed
Requires-Python: >=3.13
Requires-Dist: asyncpg>=0.31.0
Provides-Extra: all
Requires-Dist: asyncpg>=0.31.0; extra == 'all'
Provides-Extra: dev
Requires-Dist: mypy>=1.13.0; extra == 'dev'
Requires-Dist: pytest-asyncio>=0.24.0; extra == 'dev'
Requires-Dist: pytest-cov>=4.1.0; extra == 'dev'
Requires-Dist: pytest-xdist>=3.8.0; extra == 'dev'
Requires-Dist: pytest>=8.0.0; extra == 'dev'
Requires-Dist: ruff>=0.8.0; extra == 'dev'
Requires-Dist: testcontainers[postgres]>=4.0.0; extra == 'dev'
Provides-Extra: postgresql
Requires-Dist: asyncpg>=0.31.0; extra == 'postgresql'
